ai_assistant_lib/__init__.py
ai_assistant_lib/core.py
yahwin_ai_assistant_lib_new-0.1.2.dist-info/METADATA
yahwin_ai_assistant_lib_new-0.1.2.dist-info/WHEEL
yahwin_ai_assistant_lib_new-0.1.2.dist-info/top_level.txt
yahwin_ai_assistant_lib_new-0.1.2.dist-info/RECORD
