Metadata-Version: 2.4
Name: yahwin_ai_assistant_lib_new
Version: 0.1.2
Summary: A helper library for AI-powered web assistant
Author: Yahwin Lukose
Classifier: Programming Language :: Python :: 3
Classifier: License :: OSI Approved :: MIT License
Classifier: Operating System :: OS Independent
Requires-Python: >=3.6
Requires-Dist: google-generativeai
Requires-Dist: markdown
Dynamic: author
Dynamic: classifier
Dynamic: requires-dist
Dynamic: requires-python
Dynamic: summary
